clang-stubs/__init__.pyi
clang-stubs/cindex.pyi
clang-stubs/enumerations.pyi
types_clang-0.14.3.dist-info/WHEEL
types_clang-0.14.3.dist-info/METADATA
types_clang-0.14.3.dist-info/RECORD
