Metadata-Version: 2.1
Name: types-clang
Version: 0.14.3
Summary: Stubs package for Clang Python bindings
Home-page: https://github.com/tgockel/types-clang
License: Apache-2.0
Keywords: clang,stubs,typing
Author: Travis Gockel
Author-email: travis@gockelhut.com
Requires-Python: >=3.6,<4.0
Classifier: Development Status :: 3 - Alpha
Classifier: Intended Audience :: Developers
Classifier: License :: OSI Approved :: Apache Software License
Classifier: Operating System :: OS Independent
Classifier: Programming Language :: Python :: 3
Classifier: Programming Language :: Python :: 3.10
Classifier: Programming Language :: Python :: 3.6
Classifier: Programming Language :: Python :: 3.7
Classifier: Programming Language :: Python :: 3.8
Classifier: Programming Language :: Python :: 3.9
Classifier: Topic :: Software Development :: Compilers
Classifier: Typing :: Stubs Only
Project-URL: Repository, https://github.com/tgockel/types-clang
